pyparfor/__init__.py
pyparfor-0.0.1.dist-info/LICENSE
pyparfor-0.0.1.dist-info/METADATA
pyparfor-0.0.1.dist-info/WHEEL
pyparfor-0.0.1.dist-info/top_level.txt
pyparfor-0.0.1.dist-info/RECORD
